{
  "$schema": "docx-style-config-v1",
  "metadata": {
    "name": "Default",
    "description": "Clean, minimal document styling"
  },
  "page": {
    "size": "letter",
    "margins": {
      "top": "1in",
      "bottom": "1in",
      "left": "1in",
      "right": "1in"
    }
  },
  "colors": {
    "primary": "#2C4A6E",
    "accent": "#E07A38",
    "text": "#333333",
    "muted": "#666666",
    "light": "#F8F9FA",
    "success": "#27AE60",
    "warning": "#E67E22",
    "danger": "#C0392B",
    "border": "#E0E0E0"
  },
  "fonts": {
    "heading": { "name": "Arial", "bold": true },
    "body": { "name": "Arial", "size": 11 },
    "mono": { "name": "Courier New", "size": 10 }
  },
  "styles": {
    "title": {
      "font": { "name": "Arial", "size": 24, "bold": true, "color": "primary" },
      "alignment": "center",
      "spacing": { "after": 6 }
    },
    "subtitle": {
      "font": { "name": "Arial", "size": 14, "color": "muted" },
      "alignment": "center",
      "spacing": { "after": 18 }
    },
    "heading1": {
      "font": { "name": "Arial", "size": 16, "bold": true, "color": "primary" },
      "spacing": { "before": 18, "after": 10 }
    },
    "heading2": {
      "font": { "name": "Arial", "size": 13, "bold": true, "color": "primary" },
      "spacing": { "before": 14, "after": 8 }
    },
    "heading3": {
      "font": { "name": "Arial", "size": 11, "bold": true, "color": "text" },
      "spacing": { "before": 10, "after": 6 }
    },
    "body": {
      "font": { "name": "Arial", "size": 11, "color": "text" },
      "spacing": { "after": 8 }
    },
    "bullet": {
      "font": { "name": "Arial", "size": 11, "color": "text" },
      "spacing": { "after": 4 }
    }
  },
  "tables": {
    "default": {
      "headerRow": {
        "background": "#F0F0F0",
        "font": { "bold": true, "size": 11 }
      },
      "bodyRow": {
        "font": { "size": 11 }
      }
    }
  },
  "lists": {
    "bullet": { "symbol": "•", "color": "text" },
    "check": { "symbol": "✓", "color": "success" },
    "cross": { "symbol": "✗", "color": "danger" },
    "dash": { "symbol": "—", "color": "text" }
  },
  "contact": {}
}
